{
  "Sustainable Development and Ecology": [
    "Climate Change Mitigation and Adaptation",
    "Integrated Water Resource Management",
    "Wildlife Conservation and Ecology",
    "Renewable Resource Management",
    "Circular Economy and Sustainable Business Practices",
    "Sustainable Agriculture and Food Security",
    "Urban Green Spaces and Biodiversity",
    "Environmental Education and Awareness",
    "Fisheries, Animal Husbandry and Dairy",
    "Land Restoration and Reforestation",
    "Waste to Wealth"
  ],
  "Health and Well-being": [
    "Healthcare Innovation and Technology",
    "Rural Health and Well Being",
    "Traditional Medicine (AYUSH)",
    "Cancer & Metabolic Disorders",
    "Drug Abuse & Addiction",
    "Epidemiology and Pandemic Response",
    "Global Health Disparities",
    "Elderly Health care and Wellness",
    "Cognitive Neuroscience and Brain Health",
    "Mental Health and Well-being",
    "Nutrition and Dietetics",
    "Personalized Medicine and Genomics",
    "Infectious Diseases and Vaccinology",
    "Specially abled (Divyang) Wellness",
    "Maternal and Child Health",
    "Drug Design and Discovery"
  ],
  "Technology and Innovation": [
    "AI Ethics and Society",
    "Quantum Computing and Applications",
    "Innovative Educational Technologies",
    "Human-Robot Interaction",
    "Virtual Reality and Immersive Experiences",
    "Internet of Things (IoT)",
    "Big Data Analytics and Applications",
    "Blockchain Technology",
    "Smart Cities, Road and Urban Innovation",
    "Renewable Energy Technologies",
    "5G,6G & beyond",
    "Empowerment of person with Disabilities",
    "AI Based Technology & Innovation",
    "Digital twin Technology",
    "Industry 4.0",
    "Agricultural Technology & Innovation"
  ],
  "Environmental Science and Energy": [
    "Alternative Energy Solutions",
    "Sustainable Materials Development",
    "Artificial Photosynthesis and Carbon Capture",
    "Eco-Architecture and Green Buildings",
    "Ocean Sciences and Coastal Studies",
    "Soil Science and Land Management",
    "Waste Management and Recycling",
    "Environmental Monitoring and Assessment",
    "Climate Change Impacts and Resilience",
    "Energy Storage and Battery Technology",
    "Conventional Energy Sources"
  ],
  "Arts, Media, and Culture": [
    "Digital Arts and Culture",
    "Music Technology and Sound Engineering",
    "Theatre and Digital Performance",
    "Cultural Heritage Management",
    "Creative Writing and Multimedia Content",
    "Visual Arts and Design",
    "Film and Media Studies",
    "Fashion and Textile Innovation",
    "Performing Arts and Dance",
    "Art Therapy and Community Arts"
  ],
  "Social Sciences and Global Studies": [
    "Socio-Economic Policy Analysis",
    "Civil Rights and Social Equity",
    "Feminist Studies and Gender Advocacy",
    "Labour and Employment Studies",
    "Refugee and Migration Studies",
    "Geopolitics and International Security",
    "Urban Studies and Planning",
    "Rural Development and Agrarian Studies",
    "Conflict Resolution and Peace Studies",
    "Public Policy and Governance",
    "Anthropology and Cultural Studies",
    "Constitutional, Legislative & Judicial reforms"
  ],
  "Business and Economics": [
    "Business Ethics and Corporate Governance",
    "Behavioural Economics and Decision Sciences",
    "Sports Performance and Management",
    "Corporate Social Responsibility and Ethics",
    "Sustainable Tourism and Heritage Conservation",
    "Innovation and Entrepreneurship",
    "Financial Technologies (FinTech)",
    "International Trade and Global Markets",
    "Marketing and Consumer Behavior",
    "Human Resource Management and Organizational Behavior",
    "Ports, Shipping & Waterways"
  ],
  "Security and Privacy": [
    "Cybersecurity and Data Privacy",
    "Privacy and Security in the Digital Age",
    "Cyber-Physical Systems Security",
    "Blockchain for Social Impact",
    "Community Resilience and Disaster Management",
    "Digital Forensics and Incident Response",
    "Network Security and Cryptography",
    "Information Assurance and Risk Management",
    "Biometric Security and Identity Management",
    "Critical Infrastructure Protection",
    "National Security"
  ],
  "Engineering and Technology": [
    "Space Exploration and Satellite Technologies",
    "Renewable Energy Systems",
    "Nanoengineering for Medicine and Electronics (VLSI etc)",
    "Robotics and Autonomous Systems",
    "Advanced Food Production & Packaging Techniques",
    "Sustainable Manufacturing Processes",
    "Smart Grid and Energy Management",
    "Advanced Transportation Systems",
    "Biomechanics and Biomedical Engineering",
    "Additive Manufacturing and 3D Printing",
    "Atomic Energy & Nuclear Technology",
    "Mine Technology",
    "Communication Technology",
    "Supply Chain Management Technology",
    "Applied Mathematics and Statistics",
    "Laser, Plasma and Matter"
  ],
  "Education and Community Engagement": [
    "Youth Development, Training and Leadership",
    "Rural Education",
    "Train the Trainer",
    "Educational Technologies and Pedagogies",
    "Accessibility and Inclusive Design",
    "Special Needs and Inclusive Education",
    "One Health and Veterinary Sciences",
    "Community Health and Well-being",
    "Lifelong Learning and Adult Education",
    "Civic Engagement and Emotional Education",
    "Teacher Training and Professional Development",
    "Family and Child Studies",
    "Demographic Studies",
    "Equitable & Inclusive Society",
    "Women Empowerment",
    "National Educational Policy 2020",
    "Sports Infrastructure & Innovation",
    "Employment Generation & Skill Development"
  ],
  "Interdisciplinary Research": [
    "Sustainable Development Goals (SDGs) Integration",
    "Technological Innovations for Global Challenges",
    "Ethical Implications of Emerging Technologies",
    "Interdisciplinary Approaches to Climate Change",
    "Human-Machine Collaboration and Augmentation"
  ],
  "Cultural and Heritage Studies": [
    "Digital Preservation of Cultural Heritage",
    "Traditional Knowledge and Indigenous Studies",
    "Urban Heritage and Regeneration",
    "Heritage Tourism and Community Development",
    "Cultural Diplomacy and International Relations",
    "Indigenous Innovation"
  ],
  "Economic Development and Policy": [
    "Economic Development in Emerging Markets",
    "Trade Policy and Economic Integration",
    "Microfinance and Social Entrepreneurship",
    "Industrial Policy and Economic Planning",
    "Public Finance and Fiscal Policy",
    "Start Up & Entrepreneurship Training"
  ],
  "Environmental Health and Safety": [
    "Occupational Health and Safety",
    "Environmental Health Risk Assessment",
    "Toxicology and Chemical Safety",
    "Public Health Infrastructure and Policy",
    "Disaster Management",
    "Radiation studies and Solutions",
    "Waste water treatment and assessment"
  ]
} 